aolney_jupyterlab_starchat_extension/__init__.py
aolney_jupyterlab_starchat_extension/_version.py
aolney_jupyterlab_starchat_extension-0.1.3.data/data/share/jupyter/labextensions/@aolney/jupyterlab-starchat-extension/package.json
aolney_jupyterlab_starchat_extension-0.1.3.data/data/share/jupyter/labextensions/@aolney/jupyterlab-starchat-extension/static/22.8cad803e2ec64647f9a4.js
aolney_jupyterlab_starchat_extension-0.1.3.data/data/share/jupyter/labextensions/@aolney/jupyterlab-starchat-extension/static/346.b12551e5212997ae7308.js
aolney_jupyterlab_starchat_extension-0.1.3.data/data/share/jupyter/labextensions/@aolney/jupyterlab-starchat-extension/static/728.3fd0dd4c4ef7d27c57aa.js
aolney_jupyterlab_starchat_extension-0.1.3.data/data/share/jupyter/labextensions/@aolney/jupyterlab-starchat-extension/static/remoteEntry.be58e92ff8b1022bd00d.js
aolney_jupyterlab_starchat_extension-0.1.3.data/data/share/jupyter/labextensions/@aolney/jupyterlab-starchat-extension/static/style.js
aolney_jupyterlab_starchat_extension-0.1.3.data/data/share/jupyter/labextensions/@aolney/jupyterlab-starchat-extension/static/third-party-licenses.json
aolney_jupyterlab_starchat_extension-0.1.3.data/data/share/jupyter/labextensions/@aolney/jupyterlab-starchat-extension/install.json
aolney_jupyterlab_starchat_extension-0.1.3.dist-info/METADATA
aolney_jupyterlab_starchat_extension-0.1.3.dist-info/WHEEL
aolney_jupyterlab_starchat_extension-0.1.3.dist-info/licenses/LICENSE
aolney_jupyterlab_starchat_extension-0.1.3.dist-info/RECORD
