Metadata-Version: 2.3
Name: aolney_jupyterlab_starchat_extension
Version: 0.1.3
Dynamic: Keywords
Summary: A JupyterLab extension providing an interface to StarChat.
Project-URL: Homepage, https://github.com/aolney/jupyterlab-starchat-extension
Project-URL: Bug Tracker, https://github.com/aolney/jupyterlab-starchat-extension/issues
Project-URL: Repository, https://github.com/aolney/jupyterlab-starchat-extension.git
Author-email: Andrew Olney <aolney@memphis.edu>
License: BSD 3-Clause License
License-File: LICENSE
Classifier: Framework :: Jupyter
Classifier: Framework :: Jupyter :: JupyterLab
Classifier: Framework :: Jupyter :: JupyterLab :: 4
Classifier: Framework :: Jupyter :: JupyterLab :: Extensions
Classifier: Framework :: Jupyter :: JupyterLab :: Extensions :: Prebuilt
Classifier: License :: OSI Approved :: BSD License
Classifier: Programming Language :: Python
Classifier: Programming Language :: Python :: 3
Classifier: Programming Language :: Python :: 3.8
Classifier: Programming Language :: Python :: 3.9
Classifier: Programming Language :: Python :: 3.10
Classifier: Programming Language :: Python :: 3.11
Classifier: Programming Language :: Python :: 3.12
Requires-Python: >=3.8
